pwg/__init__.py
pwg-0.1.dist-info/LICENSE
pwg-0.1.dist-info/METADATA
pwg-0.1.dist-info/WHEEL
pwg-0.1.dist-info/top_level.txt
pwg-0.1.dist-info/RECORD
